google_workspace_mcp/__init__.py
google_workspace_mcp/__main__.py
google_workspace_mcp/app.py
google_workspace_mcp/config.py
google_workspace_mcp/models.py
google_workspace_mcp/auth/__init__.py
google_workspace_mcp/auth/gauth.py
google_workspace_mcp/prompts/__init__.py
google_workspace_mcp/prompts/calendar.py
google_workspace_mcp/prompts/drive.py
google_workspace_mcp/prompts/gmail.py
google_workspace_mcp/prompts/slides.py
google_workspace_mcp/resources/__init__.py
google_workspace_mcp/resources/calendar.py
google_workspace_mcp/resources/drive.py
google_workspace_mcp/resources/gmail.py
google_workspace_mcp/resources/sheets_resources.py
google_workspace_mcp/resources/slides.py
google_workspace_mcp/services/__init__.py
google_workspace_mcp/services/base.py
google_workspace_mcp/services/calendar.py
google_workspace_mcp/services/docs_service.py
google_workspace_mcp/services/drive.py
google_workspace_mcp/services/gmail.py
google_workspace_mcp/services/sheets_service.py
google_workspace_mcp/services/slides.py
google_workspace_mcp/tools/__init__.py
google_workspace_mcp/tools/calendar.py
google_workspace_mcp/tools/docs_tools.py
google_workspace_mcp/tools/drive.py
google_workspace_mcp/tools/gmail.py
google_workspace_mcp/tools/sheets_tools.py
google_workspace_mcp/tools/slides.py
google_workspace_mcp/utils/__init__.py
google_workspace_mcp/utils/markdown_slides.py
google_workspace_mcp-1.2.0.dist-info/METADATA
google_workspace_mcp-1.2.0.dist-info/WHEEL
google_workspace_mcp-1.2.0.dist-info/entry_points.txt
google_workspace_mcp-1.2.0.dist-info/RECORD
